oskb/__init__.py
oskb/cli.py
oskb/default.css
oskb/oskb.py
oskb/oskbedit.css
oskb/oskbedit.py
oskb/ui_editkey.py
oskb/ui_kbdproperties.py
oskb/ui_keyactions.py
oskb/ui_keywizard.py
oskb/ui_valueedit.py
oskb/im/__init__.py
oskb/im/uinput.py
oskb/keyboards/_new
oskb/keyboards/paddy-de
oskb/keyboards/paddy-us
oskb/keyboards/phoney-de
oskb/keyboards/phoney-us
oskb/ui/EditKey.ui
oskb/ui/KbdProperties.ui
oskb/ui/KeyActions.ui
oskb/ui/KeyWizard.ui
oskb/ui/README.md
oskb/ui/ValueEdit.ui
oskb-0.3.0.dist-info/LICENSE
oskb-0.3.0.dist-info/METADATA
oskb-0.3.0.dist-info/WHEEL
oskb-0.3.0.dist-info/entry_points.txt
oskb-0.3.0.dist-info/top_level.txt
oskb-0.3.0.dist-info/RECORD
