Metadata-Version: 2.1
Name: oskb
Version: 0.3.0
Summary: On-Screen KeyBoard
Home-page: https://github.com/ropg/oskb
Author: Rop Gonggrijp
License: MIT
Project-URL: Documentation, https://github.com/ropg/oskb/README.md
Project-URL: Source, https://github.com/ropg/oskb
Project-URL: Tracker, https://github.com/ropg/oskb/issues
Keywords: keyboard
Platform: UNKNOWN
Classifier: Development Status :: 3 - Alpha
Classifier: Programming Language :: Python :: 3
Requires-Python: >=3
Requires-Dist: pyqt5 (==5.14.0)
Requires-Dist: psutil
Requires-Dist: evdev ; platform_system == "Linux"
Requires-Dist: ewmh ; platform_system == "Linux"
